hmac.py
setup.py
micropython_hmac.egg-info/PKG-INFO
micropython_hmac.egg-info/SOURCES.txt
micropython_hmac.egg-info/dependency_links.txt
micropython_hmac.egg-info/requires.txt
micropython_hmac.egg-info/top_level.txt