Metadata-Version: 1.0
Name: micropython-hmac
Version: 3.4.2-1
Summary: CPython hmac module ported to MicroPython
Home-page: https://github.com/micropython/micropython/issues/405
Author: MicroPython Developers
Author-email: micro-python@googlegroups.com
License: Python
Platform: UNKNOWN
